{
  "symbol": "META",
  "initial_capital": 100000.0,
  "final_equity": 111378.65501552034,
  "total_return_pct": 0.11378655015520334,
  "buy_hold_return_pct": 0.29941752965728585,
  "alpha_vs_buy_hold_pct": -0.18563097950208252,
  "vol_annual": 0.250778637497982,
  "sharpe": 1.8753194204328574,
  "sortino": 4.342345997300895,
  "max_drawdown": -0.052207362229263476,
  "cagr": 0.5496276555050352,
  "num_fills": 33,
  "completed_trades": 12,
  "win_rate": 0.16666666666666666,
  "avg_win_return_pct": 0.07538414057382774,
  "avg_loss_return_pct": -0.005500308856574729,
  "expectancy_return_pct": 0.007980432715159014,
  "realized_pnl": 12114.702723015911,
  "unrealized_pnl_end": 0.0,
  "captured_buy_hold_ratio": 0.380026347440124,
  "valid_capture_ratio": 0.380026347440124,
  "tier_mode": "quantile",
  "used_tier_probs": [
    0.5170109590147743,
    0.5370109590147744,
    0.5570109590147744,
    0.5770109590147744
  ],
  "enable_trend_filter": true,
  "splits_count": 0,
  "last_split_date": null,
  "performance_guard_triggered": false,
  "performance_guard_trigger_date": null,
  "churn_cooldown_active": false,
  "recent_trades_considered_for_expectancy": 12,
  "classification": "default",
  "rollback_guard": false,
  "alpha_dollars": -18563.09795020824,
  "avg_exposure_fraction": 0.5964840534807072,
  "pct_days_in_market": 0.746031746031746
}