{
  "symbol": "RTX",
  "initial_capital": 100000.0,
  "final_equity": 118140.75821055088,
  "total_return_pct": 0.18140758210550878,
  "buy_hold_return_pct": 0.22164235095348328,
  "alpha_vs_buy_hold_pct": -0.0402347688479745,
  "vol_annual": 0.16840322010641268,
  "sharpe": 3.7552893763894994,
  "sortino": 7.011701834289835,
  "max_drawdown": -0.04151842658580529,
  "cagr": 0.854833665727976,
  "num_fills": 7,
  "completed_trades": 3,
  "win_rate": 0.6666666666666666,
  "avg_win_return_pct": 0.21978037668890116,
  "avg_loss_return_pct": -0.005711799299904904,
  "expectancy_return_pct": 0.14461631802596578,
  "realized_pnl": 18285.716598118437,
  "unrealized_pnl_end": 0.0,
  "captured_buy_hold_ratio": 0.8184698516556581,
  "tier_mode": "static",
  "used_tier_probs": [
    0.48,
    0.54,
    0.6,
    0.66
  ],
  "enable_trend_filter": true,
  "splits_count": 0,
  "last_split_date": null,
  "performance_guard_triggered": false,
  "performance_guard_trigger_date": null,
  "churn_cooldown_active": false,
  "recent_trades_considered_for_expectancy": 2,
  "classification": "strong",
  "rollback_guard": false,
  "avg_exposure_fraction": 0.7938292354100461,
  "pct_days_in_market": 0.9420289855072463
}