{
  "current_iteration": 40,
  "total_iterations": 100,
  "progress_percent": 40.0,
  "best_config_so_far": {
    "trend_5d_buy_threshold": 0.025,
    "trend_5d_sell_threshold": -0.035,
    "trend_10d_buy_threshold": 0.015,
    "trend_10d_sell_threshold": -0.02,
    "rsi_overbought": 65,
    "rsi_oversold": 15,
    "volatility_threshold": 0.06,
    "volume_ratio_threshold": 1.2
  },
  "best_performance_so_far": -61.0500688701251,
  "timestamp": "2025-08-08T19:09:29.087723",
  "completed_tests": 41
}