{
  "test_period": "2024-05-13 to 2024-08-13",
  "initial_capital": 10000,
  "nvda_momentum": {
    "total_return": -0.02602329490162114,
    "annual_return": -0.10009994286293711,
    "sharpe_ratio": -0.14307584762716452,
    "max_drawdown": -0.13140932518102255,
    "final_value": 9739.767050983788,
    "portfolio": "                 price  signal  position  holdings  daily_return  strategy_return  cum_return   total_value\nDate                                                                                                       \n2024-05-13   90.363029       0         0       0.0           NaN              NaN         NaN           NaN\n2024-05-14   91.319656       0         0       0.0      0.010586              0.0    1.000000  10000.000000\n2024-05-15   94.592339       0         0       0.0      0.035838              0.0    1.000000  10000.000000\n2024-05-16   94.321449       0         0       0.0     -0.002864             -0.0    1.000000  10000.000000\n2024-05-17   92.442200       0         0       0.0     -0.019924             -0.0    1.000000  10000.000000\n...                ...     ...       ...       ...           ...              ...         ...           ...\n2024-08-06  104.217079       0         0       0.0      0.037830              0.0    0.973977   9739.767051\n2024-08-07   98.878769       0         0       0.0     -0.051223             -0.0    0.973977   9739.767051\n2024-08-08  104.936852       0         0       0.0      0.061268              0.0    0.973977   9739.767051\n2024-08-09  104.716919       0         0       0.0     -0.002096             -0.0    0.973977   9739.767051\n2024-08-12  108.985573       0         0       0.0      0.040764              0.0    0.973977   9739.767051\n\n[63 rows x 8 columns]"
  },
  "diversified_momentum": {
    "total_return": 0.012209362832577897,
    "final_value": 10122.09362832578,
    "sharpe_ratio": 0.2412878123534235,
    "max_drawdown": -0.07644632088344441,
    "num_stocks": 10
  },
  "nvda_buy_hold": {
    "total_return": 0.20608586766213577,
    "final_value": 12060.858676621358,
    "start_price": 90.36302947998047,
    "end_price": 108.9855728149414
  }
}