{
  "symbol": "VZ",
  "initial_capital": 100000.0,
  "final_equity": 101436.94133144205,
  "total_return_pct": 0.014369413314420543,
  "buy_hold_return_pct": 0.056851456316218796,
  "alpha_vs_buy_hold_pct": -0.04248204300179825,
  "vol_annual": 0.06397064457936896,
  "sharpe": 0.9444637747279157,
  "sortino": 1.169147826326564,
  "max_drawdown": -0.014321548171456477,
  "cagr": 0.05970341142458002,
  "num_fills": 8,
  "completed_trades": 4,
  "win_rate": 0.5,
  "avg_win_return_pct": 0.041025746290760855,
  "avg_loss_return_pct": -0.0529053816603794,
  "expectancy_return_pct": -0.005939817684809272,
  "realized_pnl": 1539.2309245108386,
  "unrealized_pnl_end": 0.0,
  "captured_buy_hold_ratio": 0.25275365391688626,
  "valid_capture_ratio": 0.25275365391688626,
  "tier_mode": "static",
  "used_tier_probs": [
    0.48,
    0.54,
    0.6,
    0.66
  ],
  "enable_trend_filter": true,
  "splits_count": 0,
  "last_split_date": null,
  "performance_guard_triggered": false,
  "performance_guard_trigger_date": null,
  "churn_cooldown_active": false,
  "recent_trades_considered_for_expectancy": 4,
  "classification": "default",
  "rollback_guard": false,
  "alpha_dollars": -4248.2043001798265,
  "avg_exposure_fraction": 0.38072394328972214,
  "pct_days_in_market": 0.9523809523809523
}